flake8_warn_old_school_types.py
flake8_wot.py
flake8_wot-0.2.0.dist-info/LICENSE
flake8_wot-0.2.0.dist-info/METADATA
flake8_wot-0.2.0.dist-info/WHEEL
flake8_wot-0.2.0.dist-info/entry_points.txt
flake8_wot-0.2.0.dist-info/top_level.txt
flake8_wot-0.2.0.dist-info/RECORD
