Metadata-Version: 2.1
Name: flake8-wot
Version: 0.2.0
Summary: flake8 plugin which checks use of deprecated typing.List, typing.Dict, etc.
Home-page: https://github.com/mrijk/flake8-wot
Author: Maurits Rijk
Author-email: maurits.rijk@gmail.com
License: MIT
Platform: UNKNOWN
Classifier: License :: OSI Approved :: MIT License
Classifier: Programming Language :: Python :: 3
Classifier: Programming Language :: Python :: 3 :: Only
Classifier: Programming Language :: Python :: 3.8
Classifier: Programming Language :: Python :: 3.9
Classifier: Programming Language :: Python :: 3.10
License-File: LICENSE
Requires-Dist: flake8 (>=3.7)
